{
  "@schema": "https://raw.githubusercontent.com/slicer/slicer/master/Modules/Loadable/Markups/Resources/Schema/markups-schema-v1.0.3.json#",
  "markups": [
    {
      "type": "Fiducial",
      "coordinateSystem": "LPS",
      "coordinateUnits": "mm",
      "controlPoints": [
        {
          "id": "1",
          "label": "11m",
          "description": "",
          "associatedNodeID": "",
          "position": [
            -9.10726261138916,
            -27.053197860717773,
            7.175302982330322
          ],
          "orientation": [
            -1.0,
            0.0,
            0.0,
            0.0,
            -1.0,
            0.0,
            0.0,
            0.0,
            1.0
          ],
          "selected": true,
          "locked": false,
          "visibility": true,
          "positionStatus": "defined"
        },
        {
          "id": "2",
          "label": "11ma",
          "description": "",
          "associatedNodeID": "",
          "position": [
            -5.904880046844482,
            -27.734365463256836,
            7.884653568267822
          ],
          "orientation": [
            -1.0,
            0.0,
            0.0,
            0.0,
            -1.0,
            0.0,
            0.0,
            0.0,
            1.0
          ],
          "selected": true,
          "locked": false,
          "visibility": true,
          "positionStatus": "defined"
        },
        {
          "id": "3",
          "label": "11da",
          "description": "",
          "associatedNodeID": "",
          "position": [
            -12.190779685974121,
            -25.315710067749023,
            7.112856388092041
          ],
          "orientation": [
            -1.0,
            0.0,
            0.0,
            0.0,
            -1.0,
            0.0,
            0.0,
            0.0,
            1.0
          ],
          "selected": true,
          "locked": false,
          "visibility": true,
          "positionStatus": "defined"
        },
        {
          "id": "4",
          "label": "11mc",
          "description": "",
          "associatedNodeID": "",
          "position": [
            -4.839423656463623,
            -26.931182861328125,
            8.606243133544922
          ],
          "orientation": [
            -1.0,
            0.0,
            0.0,
            0.0,
            -1.0,
            0.0,
            0.0,
            0.0,
            1.0
          ],
          "selected": true,
          "locked": false,
          "visibility": true,
          "positionStatus": "defined"
        },
        {
          "id": "5",
          "label": "11dc",
          "description": "",
          "associatedNodeID": "",
          "position": [
            -12.765227317810059,
            -23.363143920898438,
            8.3471097946167
          ],
          "orientation": [
            -1.0,
            0.0,
            0.0,
            0.0,
            -1.0,
            0.0,
            0.0,
            0.0,
            1.0
          ],
          "selected": true,
          "locked": false,
          "visibility": true,
          "positionStatus": "defined"
        },
        {
          "id": "6",
          "label": "11bgb",
          "description": "",
          "associatedNodeID": "",
          "position": [
            -8.635485649108887,
            -22.579256057739258,
            14.776162147521973
          ],
          "orientation": [
            -1.0,
            0.0,
            0.0,
            0.0,
            -1.0,
            0.0,
            0.0,
            0.0,
            1.0
          ],
          "selected": true,
          "locked": false,
          "visibility": true,
          "positionStatus": "defined"
        },
        {
          "id": "7",
          "label": "11lgb",
          "description": "",
          "associatedNodeID": "",
          "position": [
            -6.316676616668701,
            -17.95791244506836,
            10.030413627624512
          ],
          "orientation": [
            -1.0,
            0.0,
            0.0,
            0.0,
            -1.0,
            0.0,
            0.0,
            0.0,
            1.0
          ],
          "selected": true,
          "locked": false,
          "visibility": true,
          "positionStatus": "defined"
        },
        {
          "id": "8",
          "label": "12m",
          "description": "",
          "associatedNodeID": "",
          "position": [
            -16.166662216186523,
            -21.427576065063477,
            6.362006664276123
          ],
          "orientation": [
            -1.0,
            0.0,
            0.0,
            0.0,
            -1.0,
            0.0,
            0.0,
            0.0,
            1.0
          ],
          "selected": true,
          "locked": false,
          "visibility": true,
          "positionStatus": "defined"
        },
        {
          "id": "9",
          "label": "12ma",
          "description": "",
          "associatedNodeID": "",
          "position": [
            -14.082305908203125,
            -22.786840438842773,
            7.1052165031433105
          ],
          "orientation": [
            -1.0,
            0.0,
            0.0,
            0.0,
            -1.0,
            0.0,
            0.0,
            0.0,
            1.0
          ],
          "selected": true,
          "locked": false,
          "visibility": true,
          "positionStatus": "defined"
        },
        {
          "id": "10",
          "label": "12da",
          "description": "",
          "associatedNodeID": "",
          "position": [
            -18.435422897338867,
            -19.119272232055664,
            7.376453399658203
          ],
          "orientation": [
            -1.0,
            0.0,
            0.0,
            0.0,
            -1.0,
            0.0,
            0.0,
            0.0,
            1.0
          ],
          "selected": true,
          "locked": false,
          "visibility": true,
          "positionStatus": "defined"
        },
        {
          "id": "11",
          "label": "12mc",
          "description": "",
          "associatedNodeID": "",
          "position": [
            -12.983086585998535,
            -22.57936668395996,
            8.309622764587402
          ],
          "orientation": [
            -1.0,
            0.0,
            0.0,
            0.0,
            -1.0,
            0.0,
            0.0,
            0.0,
            1.0
          ],
          "selected": true,
          "locked": false,
          "visibility": true,
          "positionStatus": "defined"
        },
        {
          "id": "12",
          "label": "12dc",
          "description": "",
          "associatedNodeID": "",
          "position": [
            -18.585975646972656,
            -17.79395294189453,
            7.958869934082031
          ],
          "orientation": [
            -1.0,
            0.0,
            0.0,
            0.0,
            -1.0,
            0.0,
            0.0,
            0.0,
            1.0
          ],
          "selected": true,
          "locked": false,
          "visibility": true,
          "positionStatus": "defined"
        },
        {
          "id": "13",
          "label": "12bgb",
          "description": "",
          "associatedNodeID": "",
          "position": [
            -15.37118911743164,
            -19.36399269104004,
            13.406582832336426
          ],
          "orientation": [
            -1.0,
            0.0,
            0.0,
            0.0,
            -1.0,
            0.0,
            0.0,
            0.0,
            1.0
          ],
          "selected": true,
          "locked": false,
          "visibility": true,
          "positionStatus": "defined"
        },
        {
          "id": "14",
          "label": "12lgb",
          "description": "",
          "associatedNodeID": "",
          "position": [
            -11.716583251953125,
            -14.98693561553955,
            9.470016479492188
          ],
          "orientation": [
            -1.0,
            0.0,
            0.0,
            0.0,
            -1.0,
            0.0,
            0.0,
            0.0,
            1.0
          ],
          "selected": true,
          "locked": false,
          "visibility": true,
          "positionStatus": "defined"
        },
        {
          "id": "15",
          "label": "13m",
          "description": "",
          "associatedNodeID": "",
          "position": [
            -21.845273971557617,
            -15.91680908203125,
            5.05718994140625
          ],
          "orientation": [
            -1.0,
            0.0,
            0.0,
            0.0,
            -1.0,
            0.0,
            0.0,
            0.0,
            1.0
          ],
          "selected": true,
          "locked": false,
          "visibility": true,
          "positionStatus": "defined"
        },
        {
          "id": "16",
          "label": "13mc",
          "description": "",
          "associatedNodeID": "",
          "position": [
            -22.790786743164062,
            -11.189909934997559,
            6.830049514770508
          ],
          "orientation": [
            -1.0,
            0.0,
            0.0,
            0.0,
            -1.0,
            0.0,
            0.0,
            0.0,
            1.0
          ],
          "selected": true,
          "locked": false,
          "visibility": true,
          "positionStatus": "defined"
        },
        {
          "id": "17",
          "label": "13dc",
          "description": "",
          "associatedNodeID": "",
          "position": [
            -18.891569137573242,
            -17.102392196655273,
            7.5495734214782715
          ],
          "orientation": [
            -1.0,
            0.0,
            0.0,
            0.0,
            -1.0,
            0.0,
            0.0,
            0.0,
            1.0
          ],
          "selected": true,
          "locked": false,
          "visibility": true,
          "positionStatus": "defined"
        },
        {
          "id": "18",
          "label": "13bgb",
          "description": "",
          "associatedNodeID": "",
          "position": [
            -21.607213973999023,
            -14.209795951843262,
            13.563252449035645
          ],
          "orientation": [
            -1.0,
            0.0,
            0.0,
            0.0,
            -1.0,
            0.0,
            0.0,
            0.0,
            1.0
          ],
          "selected": true,
          "locked": false,
          "visibility": true,
          "positionStatus": "defined"
        },
        {
          "id": "19",
          "label": "13lgb",
          "description": "",
          "associatedNodeID": "",
          "position": [
            -16.078161239624023,
            -10.387439727783203,
            8.284669876098633
          ],
          "orientation": [
            -1.0,
            0.0,
            0.0,
            0.0,
            -1.0,
            0.0,
            0.0,
            0.0,
            1.0
          ],
          "selected": true,
          "locked": false,
          "visibility": true,
          "positionStatus": "defined"
        },
        {
          "id": "20",
          "label": "14b",
          "description": "",
          "associatedNodeID": "",
          "position": [
            -22.92823028564453,
            -6.495283126831055,
            3.8176662921905518
          ],
          "orientation": [
            -1.0,
            0.0,
            0.0,
            0.0,
            -1.0,
            0.0,
            0.0,
            0.0,
            1.0
          ],
          "selected": true,
          "locked": false,
          "visibility": true,
          "positionStatus": "defined"
        },
        {
          "id": "21",
          "label": "14l",
          "description": "",
          "associatedNodeID": "",
          "position": [
            -16.19671630859375,
            -5.676149845123291,
            3.9218432903289795
          ],
          "orientation": [
            -1.0,
            0.0,
            0.0,
            0.0,
            -1.0,
            0.0,
            0.0,
            0.0,
            1.0
          ],
          "selected": true,
          "locked": false,
          "visibility": true,
          "positionStatus": "defined"
        },
        {
          "id": "22",
          "label": "14m",
          "description": "",
          "associatedNodeID": "",
          "position": [
            -19.147375106811523,
            -5.29429292678833,
            5.95704984664917
          ],
          "orientation": [
            -1.0,
            0.0,
            0.0,
            0.0,
            -1.0,
            0.0,
            0.0,
            0.0,
            1.0
          ],
          "selected": true,
          "locked": false,
          "visibility": true,
          "positionStatus": "defined"
        },
        {
          "id": "23",
          "label": "14mr",
          "description": "",
          "associatedNodeID": "",
          "position": [
            -18.5440673828125,
            -8.14871597290039,
            6.776863098144531
          ],
          "orientation": [
            -1.0,
            0.0,
            0.0,
            0.0,
            -1.0,
            0.0,
            0.0,
            0.0,
            1.0
          ],
          "selected": true,
          "locked": false,
          "visibility": true,
          "positionStatus": "defined"
        },
        {
          "id": "24",
          "label": "14dr",
          "description": "",
          "associatedNodeID": "",
          "position": [
            -19.730592727661133,
            -2.822176694869995,
            4.752709865570068
          ],
          "orientation": [
            -1.0,
            0.0,
            0.0,
            0.0,
            -1.0,
            0.0,
            0.0,
            0.0,
            1.0
          ],
          "selected": true,
          "locked": false,
          "visibility": true,
          "positionStatus": "defined"
        },
        {
          "id": "25",
          "label": "14mc",
          "description": "",
          "associatedNodeID": "",
          "position": [
            -18.676149368286133,
            -8.355966567993164,
            6.883256435394287
          ],
          "orientation": [
            -1.0,
            0.0,
            0.0,
            0.0,
            -1.0,
            0.0,
            0.0,
            0.0,
            1.0
          ],
          "selected": true,
          "locked": false,
          "visibility": true,
          "positionStatus": "defined"
        },
        {
          "id": "26",
          "label": "14dc",
          "description": "",
          "associatedNodeID": "",
          "position": [
            -19.749008178710938,
            -1.853283405303955,
            5.415782928466797
          ],
          "orientation": [
            -1.0,
            0.0,
            0.0,
            0.0,
            -1.0,
            0.0,
            0.0,
            0.0,
            1.0
          ],
          "selected": true,
          "locked": false,
          "visibility": true,
          "positionStatus": "defined"
        },
        {
          "id": "27",
          "label": "14bgb",
          "description": "",
          "associatedNodeID": "",
          "position": [
            -24.428659439086914,
            -5.731189727783203,
            9.410595893859863
          ],
          "orientation": [
            -1.0,
            0.0,
            0.0,
            0.0,
            -1.0,
            0.0,
            0.0,
            0.0,
            1.0
          ],
          "selected": true,
          "locked": false,
          "visibility": true,
          "positionStatus": "defined"
        },
        {
          "id": "28",
          "label": "14lgb",
          "description": "",
          "associatedNodeID": "",
          "position": [
            -14.85633373260498,
            -3.6557767391204834,
            7.901973247528076
          ],
          "orientation": [
            -1.0,
            0.0,
            0.0,
            0.0,
            -1.0,
            0.0,
            0.0,
            0.0,
            1.0
          ],
          "selected": true,
          "locked": false,
          "visibility": true,
          "positionStatus": "defined"
        },
        {
          "id": "29",
          "label": "15b",
          "description": "",
          "associatedNodeID": "",
          "position": [
            -24.401092529296875,
            0.6161398887634277,
            3.6050498485565186
          ],
          "orientation": [
            -1.0,
            0.0,
            0.0,
            0.0,
            -1.0,
            0.0,
            0.0,
            0.0,
            1.0
          ],
          "selected": true,
          "locked": false,
          "visibility": true,
          "positionStatus": "defined"
        },
        {
          "id": "30",
          "label": "15l",
          "description": "",
          "associatedNodeID": "",
          "position": [
            -19.59549331665039,
            2.726996660232544,
            2.4515867233276367
          ],
          "orientation": [
            -1.0,
            0.0,
            0.0,
            0.0,
            -1.0,
            0.0,
            0.0,
            0.0,
            1.0
          ],
          "selected": true,
          "locked": false,
          "visibility": true,
          "positionStatus": "defined"
        },
        {
          "id": "31",
          "label": "15m",
          "description": "",
          "associatedNodeID": "",
          "position": [
            -21.158931732177734,
            2.2849931716918945,
            4.712203502655029
          ],
          "orientation": [
            -1.0,
            0.0,
            0.0,
            0.0,
            -1.0,
            0.0,
            0.0,
            0.0,
            1.0
          ],
          "selected": true,
          "locked": false,
          "visibility": true,
          "positionStatus": "defined"
        },
        {
          "id": "32",
          "label": "15mr",
          "description": "",
          "associatedNodeID": "",
          "position": [
            -20.313566207885742,
            -0.5023665428161621,
            4.984659671783447
          ],
          "orientation": [
            -1.0,
            0.0,
            0.0,
            0.0,
            -1.0,
            0.0,
            0.0,
            0.0,
            1.0
          ],
          "selected": true,
          "locked": false,
          "visibility": true,
          "positionStatus": "defined"
        },
        {
          "id": "33",
          "label": "15dr",
          "description": "",
          "associatedNodeID": "",
          "position": [
            -22.3839168548584,
            4.93938684463501,
            4.053719997406006
          ],
          "orientation": [
            -1.0,
            0.0,
            0.0,
            0.0,
            -1.0,
            0.0,
            0.0,
            0.0,
            1.0
          ],
          "selected": true,
          "locked": false,
          "visibility": true,
          "positionStatus": "defined"
        },
        {
          "id": "34",
          "label": "15mc",
          "description": "",
          "associatedNodeID": "",
          "position": [
            -19.783510208129883,
            -0.6312932968139648,
            5.310689926147461
          ],
          "orientation": [
            -1.0,
            0.0,
            0.0,
            0.0,
            -1.0,
            0.0,
            0.0,
            0.0,
            1.0
          ],
          "selected": true,
          "locked": false,
          "visibility": true,
          "positionStatus": "defined"
        },
        {
          "id": "35",
          "label": "15dc",
          "description": "",
          "associatedNodeID": "",
          "position": [
            -22.568252563476562,
            5.416769504547119,
            4.300182819366455
          ],
          "orientation": [
            -1.0,
            0.0,
            0.0,
            0.0,
            -1.0,
            0.0,
            0.0,
            0.0,
            1.0
          ],
          "selected": true,
          "locked": false,
          "visibility": true,
          "positionStatus": "defined"
        },
        {
          "id": "36",
          "label": "15bgb",
          "description": "",
          "associatedNodeID": "",
          "position": [
            -25.37760353088379,
            0.8785567283630371,
            7.3589396476745605
          ],
          "orientation": [
            -1.0,
            0.0,
            0.0,
            0.0,
            -1.0,
            0.0,
            0.0,
            0.0,
            1.0
          ],
          "selected": true,
          "locked": false,
          "visibility": true,
          "positionStatus": "defined"
        },
        {
          "id": "37",
          "label": "15lgb",
          "description": "",
          "associatedNodeID": "",
          "position": [
            -16.467985153198242,
            4.989353179931641,
            6.786916732788086
          ],
          "orientation": [
            -1.0,
            0.0,
            0.0,
            0.0,
            -1.0,
            0.0,
            0.0,
            0.0,
            1.0
          ],
          "selected": true,
          "locked": false,
          "visibility": true,
          "positionStatus": "defined"
        },
        {
          "id": "38",
          "label": "16mb",
          "description": "",
          "associatedNodeID": "",
          "position": [
            -26.757341384887695,
            7.217363357543945,
            2.25603985786438
          ],
          "orientation": [
            -1.0,
            0.0,
            0.0,
            0.0,
            -1.0,
            0.0,
            0.0,
            0.0,
            1.0
          ],
          "selected": true,
          "locked": false,
          "visibility": true,
          "positionStatus": "defined"
        },
        {
          "id": "39",
          "label": "16db",
          "description": "",
          "associatedNodeID": "",
          "position": [
            -26.5673770904541,
            12.875065803527832,
            1.0345100164413452
          ],
          "orientation": [
            -1.0,
            0.0,
            0.0,
            0.0,
            -1.0,
            0.0,
            0.0,
            0.0,
            1.0
          ],
          "selected": true,
          "locked": false,
          "visibility": true,
          "positionStatus": "defined"
        },
        {
          "id": "40",
          "label": "16ml",
          "description": "",
          "associatedNodeID": "",
          "position": [
            -20.098209381103516,
            10.200507164001465,
            0.8762633800506592
          ],
          "orientation": [
            -1.0,
            0.0,
            0.0,
            0.0,
            -1.0,
            0.0,
            0.0,
            0.0,
            1.0
          ],
          "selected": true,
          "locked": false,
          "visibility": true,
          "positionStatus": "defined"
        },
        {
          "id": "41",
          "label": "16dl",
          "description": "",
          "associatedNodeID": "",
          "position": [
            -20.379859924316406,
            15.092582702636719,
            0.7505733966827393
          ],
          "orientation": [
            -1.0,
            0.0,
            0.0,
            0.0,
            -1.0,
            0.0,
            0.0,
            0.0,
            1.0
          ],
          "selected": true,
          "locked": false,
          "visibility": true,
          "positionStatus": "defined"
        },
        {
          "id": "42",
          "label": "16bg",
          "description": "",
          "associatedNodeID": "",
          "position": [
            -27.1551513671875,
            10.479029655456543,
            2.613569974899292
          ],
          "orientation": [
            -1.0,
            0.0,
            0.0,
            0.0,
            -1.0,
            0.0,
            0.0,
            0.0,
            1.0
          ],
          "selected": true,
          "locked": false,
          "visibility": true,
          "positionStatus": "defined"
        },
        {
          "id": "43",
          "label": "16m",
          "description": "",
          "associatedNodeID": "",
          "position": [
            -23.289993286132812,
            10.995156288146973,
            3.5632264614105225
          ],
          "orientation": [
            -1.0,
            0.0,
            0.0,
            0.0,
            -1.0,
            0.0,
            0.0,
            0.0,
            1.0
          ],
          "selected": true,
          "locked": false,
          "visibility": true,
          "positionStatus": "defined"
        },
        {
          "id": "44",
          "label": "16mr",
          "description": "",
          "associatedNodeID": "",
          "position": [
            -22.81317710876465,
            6.070772647857666,
            3.397629976272583
          ],
          "orientation": [
            -1.0,
            0.0,
            0.0,
            0.0,
            -1.0,
            0.0,
            0.0,
            0.0,
            1.0
          ],
          "selected": true,
          "locked": false,
          "visibility": true,
          "positionStatus": "defined"
        },
        {
          "id": "45",
          "label": "16dr",
          "description": "",
          "associatedNodeID": "",
          "position": [
            -23.87381935119629,
            15.977063179016113,
            2.51792311668396
          ],
          "orientation": [
            -1.0,
            0.0,
            0.0,
            0.0,
            -1.0,
            0.0,
            0.0,
            0.0,
            1.0
          ],
          "selected": true,
          "locked": false,
          "visibility": true,
          "positionStatus": "defined"
        },
        {
          "id": "46",
          "label": "16mc",
          "description": "",
          "associatedNodeID": "",
          "position": [
            -22.70961570739746,
            5.74575662612915,
            3.867556571960449
          ],
          "orientation": [
            -1.0,
            0.0,
            0.0,
            0.0,
            -1.0,
            0.0,
            0.0,
            0.0,
            1.0
          ],
          "selected": true,
          "locked": false,
          "visibility": true,
          "positionStatus": "defined"
        },
        {
          "id": "47",
          "label": "16dc",
          "description": "",
          "associatedNodeID": "",
          "position": [
            -23.596498489379883,
            16.30897331237793,
            2.676846742630005
          ],
          "orientation": [
            -1.0,
            0.0,
            0.0,
            0.0,
            -1.0,
            0.0,
            0.0,
            0.0,
            1.0
          ],
          "selected": true,
          "locked": false,
          "visibility": true,
          "positionStatus": "defined"
        },
        {
          "id": "48",
          "label": "16bgb",
          "description": "",
          "associatedNodeID": "",
          "position": [
            -28.629674911499023,
            10.96325969696045,
            6.505512714385986
          ],
          "orientation": [
            -1.0,
            0.0,
            0.0,
            0.0,
            -1.0,
            0.0,
            0.0,
            0.0,
            1.0
          ],
          "selected": true,
          "locked": false,
          "visibility": true,
          "positionStatus": "defined"
        },
        {
          "id": "49",
          "label": "16lgb",
          "description": "",
          "associatedNodeID": "",
          "position": [
            -16.82203483581543,
            12.947779655456543,
            5.693166732788086
          ],
          "orientation": [
            -1.0,
            0.0,
            0.0,
            0.0,
            -1.0,
            0.0,
            0.0,
            0.0,
            1.0
          ],
          "selected": true,
          "locked": false,
          "visibility": true,
          "positionStatus": "defined"
        },
        {
          "id": "50",
          "label": "17mb",
          "description": "",
          "associatedNodeID": "",
          "position": [
            -28.58219337463379,
            19.88337516784668,
            2.3879330158233643
          ],
          "orientation": [
            -1.0,
            0.0,
            0.0,
            0.0,
            -1.0,
            0.0,
            0.0,
            0.0,
            1.0
          ],
          "selected": true,
          "locked": false,
          "visibility": true,
          "positionStatus": "defined"
        },
        {
          "id": "51",
          "label": "17db",
          "description": "",
          "associatedNodeID": "",
          "position": [
            -27.78534507751465,
            25.270326614379883,
            3.2185399532318115
          ],
          "orientation": [
            -1.0,
            0.0,
            0.0,
            0.0,
            -1.0,
            0.0,
            0.0,
            0.0,
            1.0
          ],
          "selected": true,
          "locked": false,
          "visibility": true,
          "positionStatus": "defined"
        },
        {
          "id": "52",
          "label": "17ml",
          "description": "",
          "associatedNodeID": "",
          "position": [
            -21.559112548828125,
            21.424867630004883,
            0.47616004943847656
          ],
          "orientation": [
            -1.0,
            0.0,
            0.0,
            0.0,
            -1.0,
            0.0,
            0.0,
            0.0,
            1.0
          ],
          "selected": true,
          "locked": false,
          "visibility": true,
          "positionStatus": "defined"
        },
        {
          "id": "53",
          "label": "17dl",
          "description": "",
          "associatedNodeID": "",
          "position": [
            -22.000778198242188,
            25.9601993560791,
            2.201279878616333
          ],
          "orientation": [
            -1.0,
            0.0,
            0.0,
            0.0,
            -1.0,
            0.0,
            0.0,
            0.0,
            1.0
          ],
          "selected": true,
          "locked": false,
          "visibility": true,
          "positionStatus": "defined"
        },
        {
          "id": "54",
          "label": "17bg",
          "description": "",
          "associatedNodeID": "",
          "position": [
            -28.482370376586914,
            22.88972282409668,
            4.036946773529053
          ],
          "orientation": [
            -1.0,
            0.0,
            0.0,
            0.0,
            -1.0,
            0.0,
            0.0,
            0.0,
            1.0
          ],
          "selected": true,
          "locked": false,
          "visibility": true,
          "positionStatus": "defined"
        },
        {
          "id": "55",
          "label": "17m",
          "description": "",
          "associatedNodeID": "",
          "position": [
            -24.58112335205078,
            22.04895782470703,
            4.352432727813721
          ],
          "orientation": [
            -1.0,
            0.0,
            0.0,
            0.0,
            -1.0,
            0.0,
            0.0,
            0.0,
            1.0
          ],
          "selected": true,
          "locked": false,
          "visibility": true,
          "positionStatus": "defined"
        },
        {
          "id": "56",
          "label": "17mr",
          "description": "",
          "associatedNodeID": "",
          "position": [
            -23.861299514770508,
            17.56504249572754,
            2.9400031566619873
          ],
          "orientation": [
            -1.0,
            0.0,
            0.0,
            0.0,
            -1.0,
            0.0,
            0.0,
            0.0,
            1.0
          ],
          "selected": true,
          "locked": false,
          "visibility": true,
          "positionStatus": "defined"
        },
        {
          "id": "57",
          "label": "17dr",
          "description": "",
          "associatedNodeID": "",
          "position": [
            -24.55083656311035,
            26.63810157775879,
            4.212766647338867
          ],
          "orientation": [
            -1.0,
            0.0,
            0.0,
            0.0,
            -1.0,
            0.0,
            0.0,
            0.0,
            1.0
          ],
          "selected": true,
          "locked": false,
          "visibility": true,
          "positionStatus": "defined"
        },
        {
          "id": "58",
          "label": "17mc",
          "description": "",
          "associatedNodeID": "",
          "position": [
            -23.9932861328125,
            17.07627296447754,
            3.1684067249298096
          ],
          "orientation": [
            -1.0,
            0.0,
            0.0,
            0.0,
            -1.0,
            0.0,
            0.0,
            0.0,
            1.0
          ],
          "selected": true,
          "locked": false,
          "visibility": true,
          "positionStatus": "defined"
        },
        {
          "id": "59",
          "label": "17dc",
          "description": "",
          "associatedNodeID": "",
          "position": [
            -24.42433738708496,
            26.897348403930664,
            4.252419948577881
          ],
          "orientation": [
            -1.0,
            0.0,
            0.0,
            0.0,
            -1.0,
            0.0,
            0.0,
            0.0,
            1.0
          ],
          "selected": true,
          "locked": false,
          "visibility": true,
          "positionStatus": "defined"
        },
        {
          "id": "60",
          "label": "17bgb",
          "description": "",
          "associatedNodeID": "",
          "position": [
            -29.68402862548828,
            21.499792098999023,
            6.846516132354736
          ],
          "orientation": [
            -1.0,
            0.0,
            0.0,
            0.0,
            -1.0,
            0.0,
            0.0,
            0.0,
            1.0
          ],
          "selected": true,
          "locked": false,
          "visibility": true,
          "positionStatus": "defined"
        },
        {
          "id": "61",
          "label": "17lgb",
          "description": "",
          "associatedNodeID": "",
          "position": [
            -17.865549087524414,
            23.264328002929688,
            3.6206963062286377
          ],
          "orientation": [
            -1.0,
            0.0,
            0.0,
            0.0,
            -1.0,
            0.0,
            0.0,
            0.0,
            1.0
          ],
          "selected": true,
          "locked": false,
          "visibility": true,
          "positionStatus": "defined"
        },
        {
          "id": "62",
          "label": "21m",
          "description": "",
          "associatedNodeID": "",
          "position": [
            0.007750004529953003,
            -28.13331413269043,
            7.1591033935546875
          ],
          "orientation": [
            -1.0,
            0.0,
            0.0,
            0.0,
            -1.0,
            0.0,
            0.0,
            0.0,
            1.0
          ],
          "selected": true,
          "locked": false,
          "visibility": true,
          "positionStatus": "defined"
        },
        {
          "id": "63",
          "label": "21ma",
          "description": "",
          "associatedNodeID": "",
          "position": [
            -3.4201033115386963,
            -27.961929321289062,
            7.806006908416748
          ],
          "orientation": [
            -1.0,
            0.0,
            0.0,
            0.0,
            -1.0,
            0.0,
            0.0,
            0.0,
            1.0
          ],
          "selected": true,
          "locked": false,
          "visibility": true,
          "positionStatus": "defined"
        },
        {
          "id": "64",
          "label": "21da",
          "description": "",
          "associatedNodeID": "",
          "position": [
            3.3948662281036377,
            -27.32366371154785,
            7.125579833984375
          ],
          "orientation": [
            -1.0,
            0.0,
            0.0,
            0.0,
            -1.0,
            0.0,
            0.0,
            0.0,
            1.0
          ],
          "selected": true,
          "locked": false,
          "visibility": true,
          "positionStatus": "defined"
        },
        {
          "id": "65",
          "label": "21mc",
          "description": "",
          "associatedNodeID": "",
          "position": [
            -4.066056728363037,
            -26.83821678161621,
            8.846503257751465
          ],
          "orientation": [
            -1.0,
            0.0,
            0.0,
            0.0,
            -1.0,
            0.0,
            0.0,
            0.0,
            1.0
          ],
          "selected": true,
          "locked": false,
          "visibility": true,
          "positionStatus": "defined"
        },
        {
          "id": "66",
          "label": "21dc",
          "description": "",
          "associatedNodeID": "",
          "position": [
            4.278056621551514,
            -26.163297653198242,
            7.6461663246154785
          ],
          "orientation": [
            -1.0,
            0.0,
            0.0,
            0.0,
            -1.0,
            0.0,
            0.0,
            0.0,
            1.0
          ],
          "selected": true,
          "locked": false,
          "visibility": true,
          "positionStatus": "defined"
        },
        {
          "id": "67",
          "label": "21bgb",
          "description": "",
          "associatedNodeID": "",
          "position": [
            0.9837932586669922,
            -23.96220588684082,
            14.372193336486816
          ],
          "orientation": [
            -1.0,
            0.0,
            0.0,
            0.0,
            -1.0,
            0.0,
            0.0,
            0.0,
            1.0
          ],
          "selected": true,
          "locked": false,
          "visibility": true,
          "positionStatus": "defined"
        },
        {
          "id": "68",
          "label": "21lgb",
          "description": "",
          "associatedNodeID": "",
          "position": [
            0.30901333689689636,
            -18.830907821655273,
            9.861350059509277
          ],
          "orientation": [
            -1.0,
            0.0,
            0.0,
            0.0,
            -1.0,
            0.0,
            0.0,
            0.0,
            1.0
          ],
          "selected": true,
          "locked": false,
          "visibility": true,
          "positionStatus": "defined"
        },
        {
          "id": "69",
          "label": "22m",
          "description": "",
          "associatedNodeID": "",
          "position": [
            8.278830528259277,
            -24.748092651367188,
            6.029886722564697
          ],
          "orientation": [
            -1.0,
            0.0,
            0.0,
            0.0,
            -1.0,
            0.0,
            0.0,
            0.0,
            1.0
          ],
          "selected": true,
          "locked": false,
          "visibility": true,
          "positionStatus": "defined"
        },
        {
          "id": "70",
          "label": "22ma",
          "description": "",
          "associatedNodeID": "",
          "position": [
            5.924472808837891,
            -25.812973022460938,
            7.477632999420166
          ],
          "orientation": [
            -1.0,
            0.0,
            0.0,
            0.0,
            -1.0,
            0.0,
            0.0,
            0.0,
            1.0
          ],
          "selected": true,
          "locked": false,
          "visibility": true,
          "positionStatus": "defined"
        },
        {
          "id": "71",
          "label": "22da",
          "description": "",
          "associatedNodeID": "",
          "position": [
            10.294962882995605,
            -23.71819305419922,
            6.346216678619385
          ],
          "orientation": [
            -1.0,
            0.0,
            0.0,
            0.0,
            -1.0,
            0.0,
            0.0,
            0.0,
            1.0
          ],
          "selected": true,
          "locked": false,
          "visibility": true,
          "positionStatus": "defined"
        },
        {
          "id": "72",
          "label": "22mc",
          "description": "",
          "associatedNodeID": "",
          "position": [
            5.119836807250977,
            -25.339345932006836,
            8.272332191467285
          ],
          "orientation": [
            -1.0,
            0.0,
            0.0,
            0.0,
            -1.0,
            0.0,
            0.0,
            0.0,
            1.0
          ],
          "selected": true,
          "locked": false,
          "visibility": true,
          "positionStatus": "defined"
        },
        {
          "id": "73",
          "label": "22dc",
          "description": "",
          "associatedNodeID": "",
          "position": [
            11.314720153808594,
            -21.847383499145508,
            7.266956329345703
          ],
          "orientation": [
            -1.0,
            0.0,
            0.0,
            0.0,
            -1.0,
            0.0,
            0.0,
            0.0,
            1.0
          ],
          "selected": true,
          "locked": false,
          "visibility": true,
          "positionStatus": "defined"
        },
        {
          "id": "74",
          "label": "22bgb",
          "description": "",
          "associatedNodeID": "",
          "position": [
            8.848609924316406,
            -22.315828323364258,
            12.719226837158203
          ],
          "orientation": [
            -1.0,
            0.0,
            0.0,
            0.0,
            -1.0,
            0.0,
            0.0,
            0.0,
            1.0
          ],
          "selected": true,
          "locked": false,
          "visibility": true,
          "positionStatus": "defined"
        },
        {
          "id": "75",
          "label": "22lgb",
          "description": "",
          "associatedNodeID": "",
          "position": [
            5.827156066894531,
            -17.4209041595459,
            9.129652976989746
          ],
          "orientation": [
            -1.0,
            0.0,
            0.0,
            0.0,
            -1.0,
            0.0,
            0.0,
            0.0,
            1.0
          ],
          "selected": true,
          "locked": false,
          "visibility": true,
          "positionStatus": "defined"
        },
        {
          "id": "76",
          "label": "23m",
          "description": "",
          "associatedNodeID": "",
          "position": [
            15.367279052734375,
            -21.21687889099121,
            4.624926567077637
          ],
          "orientation": [
            -1.0,
            0.0,
            0.0,
            0.0,
            -1.0,
            0.0,
            0.0,
            0.0,
            1.0
          ],
          "selected": true,
          "locked": false,
          "visibility": true,
          "positionStatus": "defined"
        },
        {
          "id": "77",
          "label": "23mc",
          "description": "",
          "associatedNodeID": "",
          "position": [
            11.776129722595215,
            -21.119539260864258,
            6.6648268699646
          ],
          "orientation": [
            -1.0,
            0.0,
            0.0,
            0.0,
            -1.0,
            0.0,
            0.0,
            0.0,
            1.0
          ],
          "selected": true,
          "locked": false,
          "visibility": true,
          "positionStatus": "defined"
        },
        {
          "id": "78",
          "label": "23dc",
          "description": "",
          "associatedNodeID": "",
          "position": [
            17.201921463012695,
            -17.240976333618164,
            5.714456558227539
          ],
          "orientation": [
            -1.0,
            0.0,
            0.0,
            0.0,
            -1.0,
            0.0,
            0.0,
            0.0,
            1.0
          ],
          "selected": true,
          "locked": false,
          "visibility": true,
          "positionStatus": "defined"
        },
        {
          "id": "79",
          "label": "23bgb",
          "description": "",
          "associatedNodeID": "",
          "position": [
            16.043498992919922,
            -19.46979331970215,
            12.232258796691895
          ],
          "orientation": [
            -1.0,
            0.0,
            0.0,
            0.0,
            -1.0,
            0.0,
            0.0,
            0.0,
            1.0
          ],
          "selected": true,
          "locked": false,
          "visibility": true,
          "positionStatus": "defined"
        },
        {
          "id": "80",
          "label": "23lgb",
          "description": "",
          "associatedNodeID": "",
          "position": [
            11.724662780761719,
            -13.863703727722168,
            7.488792896270752
          ],
          "orientation": [
            -1.0,
            0.0,
            0.0,
            0.0,
            -1.0,
            0.0,
            0.0,
            0.0,
            1.0
          ],
          "selected": true,
          "locked": false,
          "visibility": true,
          "positionStatus": "defined"
        },
        {
          "id": "81",
          "label": "24b",
          "description": "",
          "associatedNodeID": "",
          "position": [
            20.2141170501709,
            -11.851183891296387,
            2.7104899883270264
          ],
          "orientation": [
            -1.0,
            0.0,
            0.0,
            0.0,
            -1.0,
            0.0,
            0.0,
            0.0,
            1.0
          ],
          "selected": true,
          "locked": false,
          "visibility": true,
          "positionStatus": "defined"
        },
        {
          "id": "82",
          "label": "24l",
          "description": "",
          "associatedNodeID": "",
          "position": [
            14.15311336517334,
            -9.768739700317383,
            2.517249822616577
          ],
          "orientation": [
            -1.0,
            0.0,
            0.0,
            0.0,
            -1.0,
            0.0,
            0.0,
            0.0,
            1.0
          ],
          "selected": true,
          "locked": false,
          "visibility": true,
          "positionStatus": "defined"
        },
        {
          "id": "83",
          "label": "24m",
          "description": "",
          "associatedNodeID": "",
          "position": [
            16.671110153198242,
            -10.032835960388184,
            4.7138800621032715
          ],
          "orientation": [
            -1.0,
            0.0,
            0.0,
            0.0,
            -1.0,
            0.0,
            0.0,
            0.0,
            1.0
          ],
          "selected": true,
          "locked": false,
          "visibility": true,
          "positionStatus": "defined"
        },
        {
          "id": "84",
          "label": "24mr",
          "description": "",
          "associatedNodeID": "",
          "position": [
            15.4804105758667,
            -12.637909889221191,
            5.072022914886475
          ],
          "orientation": [
            -1.0,
            0.0,
            0.0,
            0.0,
            -1.0,
            0.0,
            0.0,
            0.0,
            1.0
          ],
          "selected": true,
          "locked": false,
          "visibility": true,
          "positionStatus": "defined"
        },
        {
          "id": "85",
          "label": "24dr",
          "description": "",
          "associatedNodeID": "",
          "position": [
            17.650602340698242,
            -7.459616184234619,
            3.8379898071289062
          ],
          "orientation": [
            -1.0,
            0.0,
            0.0,
            0.0,
            -1.0,
            0.0,
            0.0,
            0.0,
            1.0
          ],
          "selected": true,
          "locked": false,
          "visibility": true,
          "positionStatus": "defined"
        },
        {
          "id": "86",
          "label": "24mc",
          "description": "",
          "associatedNodeID": "",
          "position": [
            15.50216293334961,
            -13.111506462097168,
            5.437966823577881
          ],
          "orientation": [
            -1.0,
            0.0,
            0.0,
            0.0,
            -1.0,
            0.0,
            0.0,
            0.0,
            1.0
          ],
          "selected": true,
          "locked": false,
          "visibility": true,
          "positionStatus": "defined"
        },
        {
          "id": "87",
          "label": "24dc",
          "description": "",
          "associatedNodeID": "",
          "position": [
            17.968461990356445,
            -6.6885199546813965,
            4.371389865875244
          ],
          "orientation": [
            -1.0,
            0.0,
            0.0,
            0.0,
            -1.0,
            0.0,
            0.0,
            0.0,
            1.0
          ],
          "selected": true,
          "locked": false,
          "visibility": true,
          "positionStatus": "defined"
        },
        {
          "id": "88",
          "label": "24bgb",
          "description": "",
          "associatedNodeID": "",
          "position": [
            21.609975814819336,
            -11.368145942687988,
            8.397990226745605
          ],
          "orientation": [
            -1.0,
            0.0,
            0.0,
            0.0,
            -1.0,
            0.0,
            0.0,
            0.0,
            1.0
          ],
          "selected": true,
          "locked": false,
          "visibility": true,
          "positionStatus": "defined"
        },
        {
          "id": "89",
          "label": "24lgb",
          "description": "",
          "associatedNodeID": "",
          "position": [
            12.307120323181152,
            -7.63373327255249,
            7.10435676574707
          ],
          "orientation": [
            -1.0,
            0.0,
            0.0,
            0.0,
            -1.0,
            0.0,
            0.0,
            0.0,
            1.0
          ],
          "selected": true,
          "locked": false,
          "visibility": true,
          "positionStatus": "defined"
        },
        {
          "id": "90",
          "label": "25b",
          "description": "",
          "associatedNodeID": "",
          "position": [
            22.35370445251465,
            -4.226383209228516,
            1.4923099279403687
          ],
          "orientation": [
            -1.0,
            0.0,
            0.0,
            0.0,
            -1.0,
            0.0,
            0.0,
            0.0,
            1.0
          ],
          "selected": true,
          "locked": false,
          "visibility": true,
          "positionStatus": "defined"
        },
        {
          "id": "91",
          "label": "25l",
          "description": "",
          "associatedNodeID": "",
          "position": [
            17.187602996826172,
            -2.3099732398986816,
            1.3654366731643677
          ],
          "orientation": [
            -1.0,
            0.0,
            0.0,
            0.0,
            -1.0,
            0.0,
            0.0,
            0.0,
            1.0
          ],
          "selected": true,
          "locked": false,
          "visibility": true,
          "positionStatus": "defined"
        },
        {
          "id": "92",
          "label": "25m",
          "description": "",
          "associatedNodeID": "",
          "position": [
            19.345495223999023,
            -2.8824799060821533,
            3.3243398666381836
          ],
          "orientation": [
            -1.0,
            0.0,
            0.0,
            0.0,
            -1.0,
            0.0,
            0.0,
            0.0,
            1.0
          ],
          "selected": true,
          "locked": false,
          "visibility": true,
          "positionStatus": "defined"
        },
        {
          "id": "93",
          "label": "25mr",
          "description": "",
          "associatedNodeID": "",
          "position": [
            18.345186233520508,
            -5.345059871673584,
            3.586050033569336
          ],
          "orientation": [
            -1.0,
            0.0,
            0.0,
            0.0,
            -1.0,
            0.0,
            0.0,
            0.0,
            1.0
          ],
          "selected": true,
          "locked": false,
          "visibility": true,
          "positionStatus": "defined"
        },
        {
          "id": "94",
          "label": "25dr",
          "description": "",
          "associatedNodeID": "",
          "position": [
            20.541379928588867,
            -0.3756866455078125,
            2.719169855117798
          ],
          "orientation": [
            -1.0,
            0.0,
            0.0,
            0.0,
            -1.0,
            0.0,
            0.0,
            0.0,
            1.0
          ],
          "selected": true,
          "locked": false,
          "visibility": true,
          "positionStatus": "defined"
        },
        {
          "id": "95",
          "label": "25mc",
          "description": "",
          "associatedNodeID": "",
          "position": [
            18.219146728515625,
            -5.844259738922119,
            4.16049337387085
          ],
          "orientation": [
            -1.0,
            0.0,
            0.0,
            0.0,
            -1.0,
            0.0,
            0.0,
            0.0,
            1.0
          ],
          "selected": true,
          "locked": false,
          "visibility": true,
          "positionStatus": "defined"
        },
        {
          "id": "96",
          "label": "25dc",
          "description": "",
          "associatedNodeID": "",
          "position": [
            20.614723205566406,
            0.23486328125,
            3.133273124694824
          ],
          "orientation": [
            -1.0,
            0.0,
            0.0,
            0.0,
            -1.0,
            0.0,
            0.0,
            0.0,
            1.0
          ],
          "selected": true,
          "locked": false,
          "visibility": true,
          "positionStatus": "defined"
        },
        {
          "id": "97",
          "label": "25bgb",
          "description": "",
          "associatedNodeID": "",
          "position": [
            23.971818923950195,
            -4.432826519012451,
            6.163926601409912
          ],
          "orientation": [
            -1.0,
            0.0,
            0.0,
            0.0,
            -1.0,
            0.0,
            0.0,
            0.0,
            1.0
          ],
          "selected": true,
          "locked": false,
          "visibility": true,
          "positionStatus": "defined"
        },
        {
          "id": "98",
          "label": "25lgb",
          "description": "",
          "associatedNodeID": "",
          "position": [
            14.81755542755127,
            -0.24828338623046875,
            6.095083236694336
          ],
          "orientation": [
            -1.0,
            0.0,
            0.0,
            0.0,
            -1.0,
            0.0,
            0.0,
            0.0,
            1.0
          ],
          "selected": true,
          "locked": false,
          "visibility": true,
          "positionStatus": "defined"
        },
        {
          "id": "99",
          "label": "26mb",
          "description": "",
          "associatedNodeID": "",
          "position": [
            25.853769302368164,
            1.3583731651306152,
            1.1369765996932983
          ],
          "orientation": [
            -1.0,
            0.0,
            0.0,
            0.0,
            -1.0,
            0.0,
            0.0,
            0.0,
            1.0
          ],
          "selected": true,
          "locked": false,
          "visibility": true,
          "positionStatus": "defined"
        },
        {
          "id": "100",
          "label": "26db",
          "description": "",
          "associatedNodeID": "",
          "position": [
            27.352571487426758,
            6.256366729736328,
            0.20179331302642822
          ],
          "orientation": [
            -1.0,
            0.0,
            0.0,
            0.0,
            -1.0,
            0.0,
            0.0,
            0.0,
            1.0
          ],
          "selected": true,
          "locked": false,
          "visibility": true,
          "positionStatus": "defined"
        },
        {
          "id": "101",
          "label": "26ml",
          "description": "",
          "associatedNodeID": "",
          "position": [
            19.890949249267578,
            5.5515666007995605,
            0.038483381271362305
          ],
          "orientation": [
            -1.0,
            0.0,
            0.0,
            0.0,
            -1.0,
            0.0,
            0.0,
            0.0,
            1.0
          ],
          "selected": true,
          "locked": false,
          "visibility": true,
          "positionStatus": "defined"
        },
        {
          "id": "102",
          "label": "26dl",
          "description": "",
          "associatedNodeID": "",
          "position": [
            21.30084991455078,
            9.23898696899414,
            -0.032453298568725586
          ],
          "orientation": [
            -1.0,
            0.0,
            0.0,
            0.0,
            -1.0,
            0.0,
            0.0,
            0.0,
            1.0
          ],
          "selected": true,
          "locked": false,
          "visibility": true,
          "positionStatus": "defined"
        },
        {
          "id": "103",
          "label": "26bg",
          "description": "",
          "associatedNodeID": "",
          "position": [
            27.004379272460938,
            4.286349773406982,
            1.5245599746704102
          ],
          "orientation": [
            -1.0,
            0.0,
            0.0,
            0.0,
            -1.0,
            0.0,
            0.0,
            0.0,
            1.0
          ],
          "selected": true,
          "locked": false,
          "visibility": true,
          "positionStatus": "defined"
        },
        {
          "id": "104",
          "label": "26m",
          "description": "",
          "associatedNodeID": "",
          "position": [
            23.423973083496094,
            5.479856491088867,
            2.6687233448028564
          ],
          "orientation": [
            -1.0,
            0.0,
            0.0,
            0.0,
            -1.0,
            0.0,
            0.0,
            0.0,
            1.0
          ],
          "selected": true,
          "locked": false,
          "visibility": true,
          "positionStatus": "defined"
        },
        {
          "id": "105",
          "label": "26mr",
          "description": "",
          "associatedNodeID": "",
          "position": [
            21.63938331604004,
            1.0820198059082031,
            2.5937469005584717
          ],
          "orientation": [
            -1.0,
            0.0,
            0.0,
            0.0,
            -1.0,
            0.0,
            0.0,
            0.0,
            1.0
          ],
          "selected": true,
          "locked": false,
          "visibility": true,
          "positionStatus": "defined"
        },
        {
          "id": "106",
          "label": "26dr",
          "description": "",
          "associatedNodeID": "",
          "position": [
            25.00581932067871,
            9.992802619934082,
            1.5015300512313843
          ],
          "orientation": [
            -1.0,
            0.0,
            0.0,
            0.0,
            -1.0,
            0.0,
            0.0,
            0.0,
            1.0
          ],
          "selected": true,
          "locked": false,
          "visibility": true,
          "positionStatus": "defined"
        },
        {
          "id": "107",
          "label": "26mc",
          "description": "",
          "associatedNodeID": "",
          "position": [
            21.276378631591797,
            0.7424201965332031,
            2.9441134929656982
          ],
          "orientation": [
            -1.0,
            0.0,
            0.0,
            0.0,
            -1.0,
            0.0,
            0.0,
            0.0,
            1.0
          ],
          "selected": true,
          "locked": false,
          "visibility": true,
          "positionStatus": "defined"
        },
        {
          "id": "108",
          "label": "26dc",
          "description": "",
          "associatedNodeID": "",
          "position": [
            25.11263084411621,
            10.427966117858887,
            1.8319367170333862
          ],
          "orientation": [
            -1.0,
            0.0,
            0.0,
            0.0,
            -1.0,
            0.0,
            0.0,
            0.0,
            1.0
          ],
          "selected": true,
          "locked": false,
          "visibility": true,
          "positionStatus": "defined"
        },
        {
          "id": "109",
          "label": "26bgb",
          "description": "",
          "associatedNodeID": "",
          "position": [
            28.56422996520996,
            4.0563130378723145,
            5.418186664581299
          ],
          "orientation": [
            -1.0,
            0.0,
            0.0,
            0.0,
            -1.0,
            0.0,
            0.0,
            0.0,
            1.0
          ],
          "selected": true,
          "locked": false,
          "visibility": true,
          "positionStatus": "defined"
        },
        {
          "id": "110",
          "label": "26lgb",
          "description": "",
          "associatedNodeID": "",
          "position": [
            17.198280334472656,
            8.540846824645996,
            5.399113178253174
          ],
          "orientation": [
            -1.0,
            0.0,
            0.0,
            0.0,
            -1.0,
            0.0,
            0.0,
            0.0,
            1.0
          ],
          "selected": true,
          "locked": false,
          "visibility": true,
          "positionStatus": "defined"
        },
        {
          "id": "111",
          "label": "27mb",
          "description": "",
          "associatedNodeID": "",
          "position": [
            30.535980224609375,
            12.518193244934082,
            1.2371900081634521
          ],
          "orientation": [
            -1.0,
            0.0,
            0.0,
            0.0,
            -1.0,
            0.0,
            0.0,
            0.0,
            1.0
          ],
          "selected": true,
          "locked": false,
          "visibility": true,
          "positionStatus": "defined"
        },
        {
          "id": "112",
          "label": "27db",
          "description": "",
          "associatedNodeID": "",
          "position": [
            31.263961791992188,
            17.360933303833008,
            1.8864566087722778
          ],
          "orientation": [
            -1.0,
            0.0,
            0.0,
            0.0,
            -1.0,
            0.0,
            0.0,
            0.0,
            1.0
          ],
          "selected": true,
          "locked": false,
          "visibility": true,
          "positionStatus": "defined"
        },
        {
          "id": "113",
          "label": "27ml",
          "description": "",
          "associatedNodeID": "",
          "position": [
            23.911848068237305,
            15.965270042419434,
            -0.494856595993042
          ],
          "orientation": [
            -1.0,
            0.0,
            0.0,
            0.0,
            -1.0,
            0.0,
            0.0,
            0.0,
            1.0
          ],
          "selected": true,
          "locked": false,
          "visibility": true,
          "positionStatus": "defined"
        },
        {
          "id": "114",
          "label": "27dl",
          "description": "",
          "associatedNodeID": "",
          "position": [
            25.998733520507812,
            20.2503719329834,
            1.3280166387557983
          ],
          "orientation": [
            -1.0,
            0.0,
            0.0,
            0.0,
            -1.0,
            0.0,
            0.0,
            0.0,
            1.0
          ],
          "selected": true,
          "locked": false,
          "visibility": true,
          "positionStatus": "defined"
        },
        {
          "id": "115",
          "label": "27bg",
          "description": "",
          "associatedNodeID": "",
          "position": [
            31.564817428588867,
            14.847907066345215,
            3.1670265197753906
          ],
          "orientation": [
            -1.0,
            0.0,
            0.0,
            0.0,
            -1.0,
            0.0,
            0.0,
            0.0,
            1.0
          ],
          "selected": true,
          "locked": false,
          "visibility": true,
          "positionStatus": "defined"
        },
        {
          "id": "116",
          "label": "27m",
          "description": "",
          "associatedNodeID": "",
          "position": [
            26.86396598815918,
            15.61103343963623,
            2.9184563159942627
          ],
          "orientation": [
            -1.0,
            0.0,
            0.0,
            0.0,
            -1.0,
            0.0,
            0.0,
            0.0,
            1.0
          ],
          "selected": true,
          "locked": false,
          "visibility": true,
          "positionStatus": "defined"
        },
        {
          "id": "117",
          "label": "27mr",
          "description": "",
          "associatedNodeID": "",
          "position": [
            25.743698120117188,
            11.553173065185547,
            1.7918399572372437
          ],
          "orientation": [
            -1.0,
            0.0,
            0.0,
            0.0,
            -1.0,
            0.0,
            0.0,
            0.0,
            1.0
          ],
          "selected": true,
          "locked": false,
          "visibility": true,
          "positionStatus": "defined"
        },
        {
          "id": "118",
          "label": "27dr",
          "description": "",
          "associatedNodeID": "",
          "position": [
            28.271011352539062,
            20.074026107788086,
            2.894216537475586
          ],
          "orientation": [
            -1.0,
            0.0,
            0.0,
            0.0,
            -1.0,
            0.0,
            0.0,
            0.0,
            1.0
          ],
          "selected": true,
          "locked": false,
          "visibility": true,
          "positionStatus": "defined"
        },
        {
          "id": "119",
          "label": "27mc",
          "description": "",
          "associatedNodeID": "",
          "position": [
            25.605422973632812,
            11.377379417419434,
            1.8693933486938477
          ],
          "orientation": [
            -1.0,
            0.0,
            0.0,
            0.0,
            -1.0,
            0.0,
            0.0,
            0.0,
            1.0
          ],
          "selected": true,
          "locked": false,
          "visibility": true,
          "positionStatus": "defined"
        },
        {
          "id": "120",
          "label": "27dc",
          "description": "",
          "associatedNodeID": "",
          "position": [
            28.31866455078125,
            20.343063354492188,
            3.266590118408203
          ],
          "orientation": [
            -1.0,
            0.0,
            0.0,
            0.0,
            -1.0,
            0.0,
            0.0,
            0.0,
            1.0
          ],
          "selected": true,
          "locked": false,
          "visibility": true,
          "positionStatus": "defined"
        },
        {
          "id": "121",
          "label": "27bgb",
          "description": "",
          "associatedNodeID": "",
          "position": [
            32.336856842041016,
            13.987716674804688,
            6.869489669799805
          ],
          "orientation": [
            -1.0,
            0.0,
            0.0,
            0.0,
            -1.0,
            0.0,
            0.0,
            0.0,
            1.0
          ],
          "selected": true,
          "locked": false,
          "visibility": true,
          "positionStatus": "defined"
        },
        {
          "id": "122",
          "label": "27lgb",
          "description": "",
          "associatedNodeID": "",
          "position": [
            21.80534553527832,
            19.23413848876953,
            2.749943494796753
          ],
          "orientation": [
            -1.0,
            0.0,
            0.0,
            0.0,
            -1.0,
            0.0,
            0.0,
            0.0,
            1.0
          ],
          "selected": true,
          "locked": false,
          "visibility": true,
          "positionStatus": "defined"
        }
      ],
      "display": {
        "visibility": true,
        "opacity": 1.0,
        "color": [
          0.4,
          1.0,
          1.0
        ],
        "selectedColor": [
          1.0,
          0.5000076295109483,
          0.5000076295109483
        ],
        "activeColor": [
          0.4,
          1.0,
          0.0
        ],
        "propertiesLabelVisibility": false,
        "pointLabelsVisibility": true,
        "textScale": 3.0,
        "glyphType": "Sphere3D",
        "glyphScale": 1.0,
        "glyphSize": 5.0,
        "useGlyphScale": true,
        "sliceProjection": false,
        "sliceProjectionUseFiducialColor": true,
        "sliceProjectionOutlinedBehindSlicePlane": false,
        "sliceProjectionColor": [
          1.0,
          1.0,
          1.0
        ],
        "sliceProjectionOpacity": 0.6,
        "lineThickness": 0.2,
        "lineColorFadingStart": 1.0,
        "lineColorFadingEnd": 10.0,
        "lineColorFadingSaturation": 1.0,
        "lineColorFadingHueOffset": 0.0,
        "handlesInteractive": false,
        "translationHandleVisibility": true,
        "rotationHandleVisibility": true,
        "scaleHandleVisibility": false,
        "interactionHandleScale": 3.0,
        "snapMode": "toVisibleSurface"
      }
    }
  ]
}